<annotation>
	<folder>train</folder>
	<filename>10023.bmp</filename>
	<path>/Users/temporaryuser/PycharmProjects/weapon_model/second_weapon_model/knives/images/POSITIVES_ALL/train/10023.bmp</path>
	<source>
		<database>Unknown</database>
	</source>
	<size>
		<width>100</width>
		<height>100</height>
		<depth>3</depth>
	</size>
	<segmented>0</segmented>
	<object>
		<name>knife</name>
		<pose>Unspecified</pose>
		<truncated>0</truncated>
		<difficult>0</difficult>
		<bndbox>
			<xmin>13</xmin>
			<ymin>14</ymin>
			<xmax>66</xmax>
			<ymax>85</ymax>
		</bndbox>
	</object>
</annotation>
